FOC/__init__.py
FOC/db.py
FOC/defined.py
FOC/helper.py
FOC/intervalrunner.py
FOC/main.py
freeoptionschain-0.8.dist-info/LICENSE
freeoptionschain-0.8.dist-info/METADATA
freeoptionschain-0.8.dist-info/WHEEL
freeoptionschain-0.8.dist-info/top_level.txt
freeoptionschain-0.8.dist-info/RECORD
