Metadata-Version: 2.1
Name: freeoptionschain
Version: 0.8
Summary: This library module retrieves stock options data from NASDAQ.
Home-page: https://github.com/benjamincham/free_options_chain
Author: Benjamin Cham
Author-email: benjaminchamwb@gmail.com
Project-URL: Bug Tracker, https://github.com/benjamincham/free_options_chain/issues
Project-URL: Changelog, https://github.com/benjamincham/free_options_chain/releases
Classifier: Topic :: Office/Business :: Financial :: Investment
Classifier: License :: OSI Approved :: MIT License
Classifier: Programming Language :: Python :: 3
Classifier: Programming Language :: Python :: 3.6
Classifier: Programming Language :: Python :: 3.7
Classifier: Programming Language :: Python :: 3.8
Classifier: Programming Language :: Python :: 3.9
Requires-Python: >=3.6, <4
License-File: LICENSE
Requires-Dist: requests
Requires-Dist: pandas
Requires-Dist: yfinance
Requires-Dist: yahoo-fin
Requires-Dist: pytz
Requires-Dist: urllib3
Requires-Dist: build
Requires-Dist: cython
